MANIFEST.in
README.rst
setup.py
randomlyric/__init__.py
randomlyric/__main__.py
randomlyric/randomlyric.py
randomlyric.egg-info/PKG-INFO
randomlyric.egg-info/SOURCES.txt
randomlyric.egg-info/dependency_links.txt
randomlyric.egg-info/entry_points.txt
randomlyric.egg-info/requires.txt
randomlyric.egg-info/top_level.txt